{"id": 1584, "curriculum": "2009", "gradeYear": 2020, "examYear": 2019, "month": 6, "typeGroup": "suneung", "type": "june", "subject": "영어", "subSubject": null, "solutionUrl": null, "questionUrl": "https://suneung-files.hdh061224.workers.dev/kice-v3/2020_mock06_english_q.pdf?name=2020%ED%95%99%EB%85%84%EB%8F%84%206%EB%AA%A8%20%EC%98%81%EC%96%B4%20%EB%AC%B8%EC%A0%9C%EC%A7%80.pdf", "answerUrl": "https://suneung-files.hdh061224.workers.dev/kice-v3/2020_mock06_english_a.pdf?name=2020%ED%95%99%EB%85%84%EB%8F%84%206%EB%AA%A8%20%EC%98%81%EC%96%B4%20%EC%A0%95%EB%8B%B5.pdf"}